CHANGES.txt
CONTRIBUTORS.txt
MANIFEST.in
README.txt
setup.py
src/vudo/__init__.py
src/vudo/__init__.pyc
src/vudo.skinsetup.egg-info/PKG-INFO
src/vudo.skinsetup.egg-info/SOURCES.txt
src/vudo.skinsetup.egg-info/dependency_links.txt
src/vudo.skinsetup.egg-info/entry_points.txt
src/vudo.skinsetup.egg-info/namespace_packages.txt
src/vudo.skinsetup.egg-info/not-zip-safe
src/vudo.skinsetup.egg-info/requires.txt
src/vudo.skinsetup.egg-info/top_level.txt
src/vudo/skinsetup/README.txt
src/vudo/skinsetup/__init__.py
src/vudo/skinsetup/__init__.pyc