Metadata-Version: 1.0
Name: vudo.skinsetup
Version: 0.1
Summary: Package which provides API and scripts to manage a skin directory of a VUDO app.
Home-page: git://github.com/reco/vudo.git
Author: Stefan Eletzhofer
Author-email: stefan.eletzhofer@inquant.de
License: BSD
Keywords: wsgi web bfg repoze vudo
Platform: UNKNOWN
Classifier: Programming Language :: Python
Classifier: Topic :: Software Development :: Libraries :: Python Modules
Classifier: Topic :: Internet :: WWW/HTTP
Classifier: Topic :: Internet :: WWW/HTTP :: WSGI
Classifier: Topic :: Internet :: WWW/HTTP :: WSGI :: Application
